README.md
setup.py
pigpig/__init__.py
pigpig.egg-info/PKG-INFO
pigpig.egg-info/SOURCES.txt
pigpig.egg-info/dependency_links.txt
pigpig.egg-info/not-zip-safe
pigpig.egg-info/requires.txt
pigpig.egg-info/top_level.txt