Metadata-Version: 1.2
Name: pigpig
Version: 0.0.1
Summary: A naive & useless deep learning framework.
Home-page: https://github.com/zhoudaxia233/PigPig
Author: Zheng Zhou
Author-email: yootaoo@gmail.com
License: MIT
Keywords: deep-learning
Platform: UNKNOWN
Requires-Python: >=3.6
